merklelib/__init__.py
merklelib/compat.py
merklelib/format.py
merklelib/merkle.py
merklelib/utils.py
merklelib-1.0.dist-info/DESCRIPTION.rst
merklelib-1.0.dist-info/METADATA
merklelib-1.0.dist-info/RECORD
merklelib-1.0.dist-info/WHEEL
merklelib-1.0.dist-info/metadata.json
merklelib-1.0.dist-info/top_level.txt
