Metadata-Version: 2.1
Name: merklelib
Version: 1.0
Summary: Merkle tree and its variations for easier data verification.
Home-page: https://github.com/vpaliy/merkle-trees
Author: Vasyl Paliy
Author-email: vpaliy97@gmail.com
License: MIT
Platform: UNKNOWN
Classifier: Intended Audience :: Developers
Classifier: Operating System :: OS Independent
Classifier: Programming Language :: Python
Classifier: Programming Language :: Python :: 3
Classifier: Programming Language :: Python :: 3.4
Classifier: Programming Language :: Python :: 3.5
Classifier: Programming Language :: Python :: 3.6
Requires-Python: >=2.7
